rbac_permissions
