Metadata-Version: 2.1
Name: django-rbac-permissions
Version: 0.4
Summary: A Django app which enables RBAC authorization.
Home-page: UNKNOWN
Author: Can Arsoy
Author-email: can@voltlines.com
License: BSD-3-Clause  # Example license
Platform: UNKNOWN
Classifier: Environment :: Web Environment
Classifier: Framework :: Django
Classifier: Intended Audience :: Developers
Classifier: License :: OSI Approved :: BSD License
Classifier: Operating System :: OS Independent
Classifier: Programming Language :: Python
Classifier: Programming Language :: Python :: 3
